misguided_xml/__init__.py
misguided_xml/_metadata.py
misguided_xml/xml.py
misguided_xml/old_unit_tests/__init__.py
misguided_xml/old_unit_tests/from_xml.py
misguided_xml/old_unit_tests/xml__test.py
misguided_xml/unittests/__init__.py
misguided_xml-1.1.0.dist-info/LICENSE.txt
misguided_xml-1.1.0.dist-info/METADATA
misguided_xml-1.1.0.dist-info/WHEEL
misguided_xml-1.1.0.dist-info/entry_points.txt
misguided_xml-1.1.0.dist-info/top_level.txt
misguided_xml-1.1.0.dist-info/RECORD
