Metadata-Version: 2.1
Name: misguided-xml
Version: 1.1.0
Summary: UNKNOWN
Home-page: https://bitbucket.org/daycoder/cachingutil.git
Author: Hywel Thomas
Author-email: hywel.thomas@mac.com
License: MIT
Download-URL: https://bitbucket.org/daycoder/cachingutil.git/get/1.1.0.tar
Keywords: misguided_xml
Platform: UNKNOWN
Classifier: Development Status :: 3 - Alpha
Classifier: Intended Audience :: Developers
Classifier: License :: OSI Approved :: MIT License
Classifier: Programming Language :: Python :: 2
Classifier: Programming Language :: Python :: 2.7
Classifier: Programming Language :: Python :: 3
Classifier: Programming Language :: Python :: 3.6
Classifier: Topic :: Utilities
Requires-Dist: pip (>=18.1)
Requires-Dist: future (>=0.16.0)
Requires-Dist: fdutil (>=1.13.0)
Requires-Dist: conversionutil (>=1.4.2)
Provides-Extra: test
